odoo10_addon_base_suspend_security-10.0.1.0.0-py2.7-nspkg.pth
odoo10_addon_base_suspend_security-10.0.1.0.0.dist-info/top_level.txt
odoo10_addon_base_suspend_security-10.0.1.0.0.dist-info/WHEEL
odoo10_addon_base_suspend_security-10.0.1.0.0.dist-info/RECORD
odoo10_addon_base_suspend_security-10.0.1.0.0.dist-info/metadata.json
odoo10_addon_base_suspend_security-10.0.1.0.0.dist-info/DESCRIPTION.rst
odoo10_addon_base_suspend_security-10.0.1.0.0.dist-info/METADATA
odoo10_addon_base_suspend_security-10.0.1.0.0.dist-info/namespace_packages.txt
odoo/addons/base_suspend_security/__manifest__.py
odoo/addons/base_suspend_security/base_suspend_security.py
odoo/addons/base_suspend_security/__init__.py
odoo/addons/base_suspend_security/README.rst
odoo/addons/base_suspend_security/models/ir_model_access.py
odoo/addons/base_suspend_security/models/ir_rule.py
odoo/addons/base_suspend_security/models/__init__.py
odoo/addons/base_suspend_security/models/base.py
odoo/addons/base_suspend_security/models/res_users.py
odoo/addons/base_suspend_security/i18n/zh_CN.po
odoo/addons/base_suspend_security/i18n/it.po
odoo/addons/base_suspend_security/i18n/es.po
odoo/addons/base_suspend_security/i18n/tr.po
odoo/addons/base_suspend_security/i18n/hr.po
odoo/addons/base_suspend_security/i18n/sl.po
odoo/addons/base_suspend_security/i18n/de.po
odoo/addons/base_suspend_security/i18n/fr.po
odoo/addons/base_suspend_security/i18n/pt_BR.po
odoo/addons/base_suspend_security/i18n/hr_HR.po
odoo/addons/base_suspend_security/tests/__init__.py
odoo/addons/base_suspend_security/tests/test_base_suspend_security.py
odoo/addons/base_suspend_security/static/description/icon.png
